{"version":1,"resource":"vscode-remote://ssh-remote%2Bcloud2/home/davineves/app.py","entries":[{"id":"tasu.py","timestamp":1761833809174},{"id":"DIAk.py","source":"Add '# type: ignore' to suppress warning","timestamp":1761833849186},{"id":"ixRf.py","timestamp":1761847556490},{"id":"S4cA.py","timestamp":1761847789286},{"id":"cq65.py","timestamp":1761848034298},{"id":"YV0R.py","timestamp":1761848087894},{"id":"fMrO.py","timestamp":1761848174190},{"id":"CH0g.py","timestamp":1761926565796},{"id":"L2S6.py","timestamp":1761926586628},{"id":"8H4V.py","timestamp":1761926598936},{"id":"en00.py","source":"Chat Edit","timestamp":1761953572619}]}